Metadata-Version: 2.1
Name: django-collectd-rest
Version: 0.2.4
Summary: A simple Django application to demonstrate RRD plots generated by collectd or any other rrd data
Author-email: "Matwey V. Kornilov" <matwey.kornilov@gmail.com>
License: BSD-2-Clause
Project-URL: Repository, https://github.com/matwey/django-collectd-rest.git
Project-URL: Issues, https://github.com/matwey/django-collectd-rest/issues
Classifier: Development Status :: 5 - Production/Stable
Classifier: Environment :: Web Environment
Classifier: Framework :: Django
Classifier: Intended Audience :: Developers
Classifier: License :: OSI Approved :: BSD License
Classifier: Operating System :: OS Independent
Classifier: Programming Language :: Python :: 3
Classifier: Programming Language :: Python
Classifier: Topic :: Internet :: WWW/HTTP :: Dynamic Content
Classifier: Topic :: Internet :: WWW/HTTP
Requires-Python: >=3.7
License-File: LICENSE
Requires-Dist: djangorestframework
Provides-Extra: dev
Requires-Dist: mock; extra == "dev"
Requires-Dist: pytest; extra == "dev"
Requires-Dist: pytest-django; extra == "dev"
